keyrt/__init__.py
keyrt/aioclient.py
keyrt/models/__init__.py
keyrt/models/cameras.py
keyrt/models/codes.py
keyrt/models/devices.py
keyrt/models/tokens.py
keyrt/models/user.py
keyrt-0.0.4a2.dist-info/METADATA
keyrt-0.0.4a2.dist-info/WHEEL
keyrt-0.0.4a2.dist-info/top_level.txt
keyrt-0.0.4a2.dist-info/RECORD
