Metadata-Version: 2.1
Name: keyrt
Version: 0.0.4a2
Summary: KeyRT
Home-page: https://github.com/WhiteApfel/keyrt
Author: WhiteApfel
Author-email: white@pfel.ru
License: Mozilla Public License 2.0
Requires-Dist: httpx (==0.24.0)
Requires-Dist: pydantic (==1.10.7)
